{
	"style":	null,
	"props":	{
		"id":	"IturHul",
		"component_path":	"IturHul/",
		"component_uniquename":	"IturHul_IturHul"
	},
	"coordinates":	{
		"x":	380,
		"y":	182,
		"width":	519,
		"height":	528
	},
	"hint":	null,
	"controlType":	null,
	"children":	[
		{
			"style":	null,
			"props":	{
				"id":	"vSearch",
				"mgformat":	"mgFormat",
				"attribute":	"A",
				"common_line_id":	"line9"
			},
			"coordinates":	{
				"x":	12,
				"y":	12,
				"width":	403,
				"height":	20
			},
			"hint":	null,
			"controlType":	"T",
			"children":	null
		},
		{
			"style":	null,
			"props":	{
				"id":	"btnAdd",
				"format":	"Add",
				"common_line_id":	"line9"
			},
			"coordinates":	{
				"x":	421,
				"y":	9,
				"width":	80,
				"height":	24
			},
			"hint":	null,
			"controlType":	"B",
			"children":	null
		},
		{
			"style":	null,
			"props":	{
				"id":	"Table33554433",
				"table_row_height":	26,
				"table_title_height":	19,
				"common_line_id":	"line46"
			},
			"coordinates":	{
				"x":	47,
				"y":	46,
				"width":	414,
				"height":	458
			},
			"hint":	null,
			"controlType":	"A",
			"children":	[
				{
					"style":	null,
					"props":	{
						"id":	"Column33554442",
						"column_title":	"Style",
						"is_table_child":	true,
						"web_style":	2
					},
					"coordinates":	{
						"width":	154
					},
					"hint":	null,
					"controlType":	"K",
					"children":	[
						{
							"style":	null,
							"props":	{
								"id":	"eitor4hul_Style",
								"mgformat":	"mgFormat",
								"attribute":	"A",
								"is_table_child":	true,
								"web_style":	2,
								"common_line_id":	"line69"
							},
							"coordinates":	{
								"x":	51,
								"y":	69,
								"width":	146,
								"height":	20
							},
							"hint":	null,
							"controlType":	"T",
							"children":	null
						}
					]
				},
				{
					"style":	null,
					"props":	{
						"id":	"Column33554444",
						"column_title":	"Location",
						"is_table_child":	true,
						"web_style":	2
					},
					"coordinates":	{
						"width":	154
					},
					"hint":	null,
					"controlType":	"K",
					"children":	[
						{
							"style":	null,
							"props":	{
								"id":	"eitor4hul_Location",
								"mgformat":	"mgFormat",
								"attribute":	"A",
								"is_table_child":	true,
								"web_style":	2,
								"common_line_id":	"line69"
							},
							"coordinates":	{
								"x":	205,
								"y":	69,
								"width":	146,
								"height":	20
							},
							"hint":	null,
							"controlType":	"T",
							"children":	null
						}
					]
				},
				{
					"style":	null,
					"props":	{
						"id":	"cEdit",
						"is_table_child":	true,
						"web_style":	2
					},
					"coordinates":	{
						"width":	49
					},
					"hint":	null,
					"controlType":	"K",
					"children":	[
						{
							"style":	null,
							"props":	{
								"id":	"bEdit",
								"format":	"Edit",
								"is_table_child":	true,
								"web_style":	2,
								"row_editing_type":	0,
								"common_line_id":	"line69"
							},
							"coordinates":	{
								"x":	359,
								"y":	69,
								"width":	41,
								"height":	22
							},
							"hint":	null,
							"controlType":	"B",
							"children":	null
						}
					]
				},
				{
					"style":	null,
					"props":	{
						"id":	"cDel",
						"is_table_child":	true,
						"web_style":	2
					},
					"coordinates":	{
						"width":	49
					},
					"hint":	null,
					"controlType":	"K",
					"children":	[
						{
							"style":	null,
							"props":	{
								"id":	"bDel",
								"format":	"Del",
								"is_table_child":	true,
								"web_style":	2,
								"row_editing_type":	0,
								"common_line_id":	"line69"
							},
							"coordinates":	{
								"x":	408,
								"y":	69,
								"width":	41,
								"height":	22
							},
							"hint":	null,
							"controlType":	"B",
							"children":	null
						}
					]
				}
			]
		}
	]
}